<?xml version="1.0" encoding="utf-8"?>
<search>
  
  
  
  <entry>
    <title>test</title>
    <link href="/web/cl9fmahpy0002wsun7dsoe257/"/>
    <url>/web/cl9fmahpy0002wsun7dsoe257/</url>
    
    <content type="html"><![CDATA[]]></content>
    
    
    <categories>
      
      <category>博客维护</category>
      
    </categories>
    
    
  </entry>
  
  
  
  <entry>
    <title>hexo</title>
    <link href="/web/cl9fmahpu0001wsun3i4kad2t/"/>
    <url>/web/cl9fmahpu0001wsun3i4kad2t/</url>
    
    <content type="html"><![CDATA[<p>dddddd</p>]]></content>
    
    
    <categories>
      
      <category>博客维护</category>
      
    </categories>
    
    
    <tags>
      
      <tag>hexo</tag>
      
    </tags>
    
  </entry>
  
  
  
  
</search>
